floyd/__init__.py
floyd/__main__.py
floyd/version.py
floyd_python-0.17.4.dist-info/LICENSE
floyd_python-0.17.4.dist-info/METADATA
floyd_python-0.17.4.dist-info/WHEEL
floyd_python-0.17.4.dist-info/entry_points.txt
floyd_python-0.17.4.dist-info/top_level.txt
floyd_python-0.17.4.dist-info/RECORD
