Metadata-Version: 2.1
Name: floyd-python
Version: 0.17.4
Summary: A parser generator and interpreter framework for Python. 
Author-email: Dirk Pranke <dpranke@chromium.org>
License: Apache License
Project-URL: Repository, https://github.com/dpranke/floyd-python
Project-URL: Issues, https://github.com/dpranke/floyd-python/issues
Project-URL: Changelog, https://github.com/dpranke/floyd-python/blob/master/README.md
Classifier: Development Status :: 3 - Alpha
Classifier: Intended Audience :: Developers
Classifier: License :: OSI Approved :: Apache Software License
Classifier: Programming Language :: Python :: 3
Classifier: Programming Language :: Python :: 3.8
Classifier: Programming Language :: Python :: 3.9
Classifier: Programming Language :: Python :: 3.10
Classifier: Programming Language :: Python :: 3.11
Classifier: Programming Language :: Python :: 3.12
Classifier: Programming Language :: Python :: 3.13
Requires-Python: >=3.8.0
License-File: LICENSE
Provides-Extra: dev
Requires-Dist: build ==1.2.2.post1 ; extra == 'dev'
Requires-Dist: coverage ==7.5.3 ; extra == 'dev'
Requires-Dist: mypy ==1.13.0 ; extra == 'dev'
Requires-Dist: pip ==24.3.1 ; extra == 'dev'
Requires-Dist: pylint ==3.2.3 ; extra == 'dev'
Requires-Dist: ruff ==0.7.3 ; extra == 'dev'
Requires-Dist: twine ==5.1.1 ; extra == 'dev'
Requires-Dist: uv ==0.5.1 ; extra == 'dev'
